<?xml version="1.0" encoding="UTF-8"?><definitions xmlns="http://www.omg.org/spec/BPMN/20100524/MODEL" xmlns:bpmndi="http://www.omg.org/spec/BPMN/20100524/DI" xmlns:omgdc="http://www.omg.org/spec/DD/20100524/DC" xmlns:omgdi="http://www.omg.org/spec/DD/20100524/DI" xmlns:signavio="http://www.signavio.com" xmlns:xsi="http://www.w3.org/2001/XMLSchema-instance" exporter="Signavio Process Editor, http://www.signavio.com" exporterVersion="12.5.2" expressionLanguage="http://www.w3.org/TR/XPath" id="sid-1f4158aa-7f36-4911-95f1-90fe98f3746e" targetNamespace="http://www.signavio.com" typeLanguage="http://www.w3.org/2001/XMLSchema" xsi:schemaLocation="http://www.omg.org/spec/BPMN/20100524/MODEL http://www.omg.org/spec/BPMN/2.0/20100501/BPMN20.xsd">
   <collaboration id="sid-a0885187-eeca-4f85-bd14-b108c6867dac">
      <extensionElements>
         <signavio:signavioDiagramMetaData metaKey="prozessreifegrad" metaValue=""/>
         <signavio:signavioDiagramMetaData metaKey="iso9000ff" metaValue=""/>
         <signavio:signavioDiagramMetaData metaKey="processgoal" metaValue=""/>
         <signavio:signavioDiagramMetaData metaKey="meta-prozessverantwortlicher" metaValue=""/>
         <signavio:signavioDiagramMetaData metaKey="revisionid" metaValue="9c37674e1ecd4019a3b74863b7883e7b"/>
      </extensionElements>
      <participant id="sid-254C1C08-44FB-4435-B4CE-250D40804BB0" name="Farming Bot" processRef="sid-281A3BB3-B536-4EB0-A45D-139689FD6743">
         <extensionElements>
            <signavio:signavioMetaData metaKey="bgcolor" metaValue="#ffffff"/>
            <signavio:signavioMetaData metaKey="bordercolor" metaValue="#000000"/>
         </extensionElements>
      </participant>
   </collaboration>
   <process id="sid-281A3BB3-B536-4EB0-A45D-139689FD6743" isClosed="false" isExecutable="false" name="Farming Bot" processType="None">
      <extensionElements/>
      <laneSet id="sid-fa112854-37e5-4c1b-b05b-d1c5b7f29050">
         <lane id="sid-02EB9EA9-F233-448D-90FD-457933AC17F3">
            <extensionElements>
               <signavio:signavioMetaData metaKey="bgcolor" metaValue=""/>
               <signavio:signavioMetaData metaKey="bordercolor" metaValue="#000000"/>
            </extensionElements>
            <flowNodeRef>sid-FCD05023-BAA3-4065-BD1F-5FA697C9FE7E</flowNodeRef>
            <flowNodeRef>sid-995C1ED2-823B-4D1B-A156-30C091163C03</flowNodeRef>
            <flowNodeRef>sid-8A17AEF6-4F45-449B-9E37-C93642245520</flowNodeRef>
            <flowNodeRef>sid-72387810-5DD4-4BC7-98B5-C0D192A43F71</flowNodeRef>
            <flowNodeRef>sid-36AE0908-FCB7-44CB-B542-915C24B8794A</flowNodeRef>
            <flowNodeRef>sid-AECEBC4B-A695-4F3D-8F32-48D648544277</flowNodeRef>
            <flowNodeRef>sid-C6E897EF-0C45-4A5C-9F96-9E57B03064BE</flowNodeRef>
            <flowNodeRef>sid-94315044-9369-43F1-AF4F-309996396228</flowNodeRef>
            <flowNodeRef>sid-8CF02890-16FE-4414-9B3F-E2F0B5B49F15</flowNodeRef>
            <flowNodeRef>sid-4B6AFED9-ECB7-4D76-B7BF-600982C3A1F4</flowNodeRef>
            <flowNodeRef>sid-69A5168B-B590-4025-BB44-9C7C9BD263E4</flowNodeRef>
            <flowNodeRef>sid-CB974ECB-BE0B-48AF-B590-2D3195BC6F8D</flowNodeRef>
            <flowNodeRef>sid-459CC583-20CC-46D9-A6E2-56B0F507912C</flowNodeRef>
            <flowNodeRef>sid-8E40E2E5-D9F1-43F8-AA5B-BCDF270149E7</flowNodeRef>
            <flowNodeRef>sid-6BFC7FF3-96DF-43A2-9269-22B4C475EEBD</flowNodeRef>
            <flowNodeRef>sid-C46919CE-C515-4092-B5DC-36A012476AE8</flowNodeRef>
            <flowNodeRef>sid-7AC1439B-F977-44D0-BD81-AA73D744F985</flowNodeRef>
            <flowNodeRef>sid-B053F60B-3197-4F90-9829-A4CDC7ED3B84</flowNodeRef>
            <flowNodeRef>sid-79623788-F448-42F1-B711-109493412590</flowNodeRef>
            <flowNodeRef>sid-885A648A-B0C9-47D2-9624-906B1CC92140</flowNodeRef>
            <flowNodeRef>sid-C429E5F8-145E-4C77-942A-508E2FD37DE3</flowNodeRef>
            <flowNodeRef>sid-2815C8D6-40FD-41A6-BB74-6F10C4E0BEEF</flowNodeRef>
            <flowNodeRef>sid-59C95768-76C7-461E-BEC4-55D9EF1727BA</flowNodeRef>
            <flowNodeRef>sid-06562524-6558-43F4-99A3-88883DBB94C8</flowNodeRef>
         </lane>
      </laneSet>
      <startEvent id="sid-FCD05023-BAA3-4065-BD1F-5FA697C9FE7E" name="Start">
         <extensionElements>
            <signavio:signavioMetaData metaKey="bgcolor" metaValue="#ffffff"/>
            <signavio:signavioMetaData metaKey="bordercolor" metaValue="#000000"/>
            <signavio:signavioMetaData metaKey="vorgngerprozesse" metaValue="[]"/>
         </extensionElements>
         <outgoing>sid-752C7D6F-B222-4C87-A0C2-F68190C73039</outgoing>
      </startEvent>
      <userTask completionQuantity="1" id="sid-995C1ED2-823B-4D1B-A156-30C091163C03" implementation="##WebService" isForCompensation="false" name="choose recources&#10;(max 10)" startQuantity="1">
         <extensionElements>
            <signavio:signavioMetaData metaKey="bgcolor" metaValue="#FFFFCC"/>
            <signavio:signavioMetaData metaKey="bordercolor" metaValue="#000000"/>
            <signavio:signavioMetaData metaKey="erteiltfreigabe" metaValue=""/>
            <signavio:signavioMetaData metaKey="wirdkonsultiert" metaValue="[]"/>
            <signavio:signavioMetaData metaKey="externaldocuments" metaValue="[]"/>
            <signavio:signavioMetaData metaKey="meta-risikomanagement" metaValue=""/>
            <signavio:signavioMetaData metaKey="wirdinformiert" metaValue="[]"/>
         </extensionElements>
         <incoming>sid-752C7D6F-B222-4C87-A0C2-F68190C73039</incoming>
         <outgoing>sid-A80FA3E6-7C70-4133-A09C-819AEE471673</outgoing>
      </userTask>
      <userTask completionQuantity="1" id="sid-8A17AEF6-4F45-449B-9E37-C93642245520" implementation="##WebService" isForCompensation="false" name="new recources" startQuantity="1">
         <extensionElements>
            <signavio:signavioMetaData metaKey="bgcolor" metaValue="#ffffcc"/>
            <signavio:signavioMetaData metaKey="bordercolor" metaValue="#000000"/>
            <signavio:signavioMetaData metaKey="erteiltfreigabe" metaValue=""/>
            <signavio:signavioMetaData metaKey="wirdkonsultiert" metaValue="[]"/>
            <signavio:signavioMetaData metaKey="externaldocuments" metaValue="[]"/>
            <signavio:signavioMetaData metaKey="meta-risikomanagement" metaValue=""/>
            <signavio:signavioMetaData metaKey="wirdinformiert" metaValue="[]"/>
         </extensionElements>
         <incoming>sid-4557CBC3-5064-4412-9BE8-CFF545235FE6</incoming>
         <outgoing>sid-AFC848A3-F230-452C-A79F-2372D0D24F7F</outgoing>
      </userTask>
      <exclusiveGateway gatewayDirection="Diverging" id="sid-72387810-5DD4-4BC7-98B5-C0D192A43F71" name="choose new recources?">
         <extensionElements>
            <signavio:signavioMetaData metaKey="bgcolor" metaValue="#ffffff"/>
            <signavio:signavioMetaData metaKey="bordercolor" metaValue="#000000"/>
            <signavio:signavioLabel align="center" bottom="false" left="false" ref="text_name" right="false" top="true" valign="bottom" x="20.0" y="-8.0"/>
         </extensionElements>
         <incoming>sid-C29E8122-E5AD-4431-A155-8979E7BDDDD5</incoming>
         <outgoing>sid-4557CBC3-5064-4412-9BE8-CFF545235FE6</outgoing>
         <outgoing>sid-F64341FD-A44D-4B9B-984B-0B20BD9E9384</outgoing>
      </exclusiveGateway>
      <exclusiveGateway gatewayDirection="Diverging" id="sid-36AE0908-FCB7-44CB-B542-915C24B8794A" name="">
         <extensionElements>
            <signavio:signavioMetaData metaKey="bgcolor" metaValue="#ffffff"/>
            <signavio:signavioMetaData metaKey="bordercolor" metaValue="#000000"/>
         </extensionElements>
         <incoming>sid-314D740D-DE5E-4ADE-A717-7F68D0EC996E</incoming>
         <outgoing>sid-EAE6212D-1F02-445E-BC43-69EDBBE56BB1</outgoing>
         <outgoing>sid-1168F775-4B9E-42B6-A602-4DE7F0193063</outgoing>
         <outgoing>sid-E1940EFA-FFDB-4513-8CF5-385595943FED</outgoing>
      </exclusiveGateway>
      <userTask completionQuantity="1" id="sid-AECEBC4B-A695-4F3D-8F32-48D648544277" implementation="##WebService" isForCompensation="false" name="brag to friends" startQuantity="1">
         <extensionElements>
            <signavio:signavioMetaData metaKey="bgcolor" metaValue="#ffffcc"/>
            <signavio:signavioMetaData metaKey="bordercolor" metaValue="#000000"/>
            <signavio:signavioMetaData metaKey="erteiltfreigabe" metaValue=""/>
            <signavio:signavioMetaData metaKey="wirdkonsultiert" metaValue="[]"/>
            <signavio:signavioMetaData metaKey="externaldocuments" metaValue="[]"/>
            <signavio:signavioMetaData metaKey="meta-risikomanagement" metaValue=""/>
            <signavio:signavioMetaData metaKey="wirdinformiert" metaValue="[]"/>
         </extensionElements>
         <incoming>sid-E1940EFA-FFDB-4513-8CF5-385595943FED</incoming>
         <outgoing>sid-E0704CB7-47D0-4C8D-99E4-C30091DF8219</outgoing>
      </userTask>
      <userTask completionQuantity="1" id="sid-C6E897EF-0C45-4A5C-9F96-9E57B03064BE" implementation="##WebService" isForCompensation="false" name="send materials to friends" startQuantity="1">
         <extensionElements>
            <signavio:signavioMetaData metaKey="bgcolor" metaValue="#ffffcc"/>
            <signavio:signavioMetaData metaKey="bordercolor" metaValue="#000000"/>
            <signavio:signavioMetaData metaKey="erteiltfreigabe" metaValue=""/>
            <signavio:signavioMetaData metaKey="wirdkonsultiert" metaValue="[]"/>
            <signavio:signavioMetaData metaKey="externaldocuments" metaValue="[]"/>
            <signavio:signavioMetaData metaKey="meta-risikomanagement" metaValue=""/>
            <signavio:signavioMetaData metaKey="wirdinformiert" metaValue="[]"/>
         </extensionElements>
         <incoming>sid-1168F775-4B9E-42B6-A602-4DE7F0193063</incoming>
         <outgoing>sid-9B38DB9C-7620-49F5-9316-A37894EFB89B</outgoing>
      </userTask>
      <exclusiveGateway gatewayDirection="Converging" id="sid-94315044-9369-43F1-AF4F-309996396228" name="">
         <extensionElements>
            <signavio:signavioMetaData metaKey="bgcolor" metaValue="#ffffff"/>
            <signavio:signavioMetaData metaKey="bordercolor" metaValue="#000000"/>
         </extensionElements>
         <incoming>sid-E0704CB7-47D0-4C8D-99E4-C30091DF8219</incoming>
         <incoming>sid-9B38DB9C-7620-49F5-9316-A37894EFB89B</incoming>
         <incoming>sid-3639D970-8627-48EE-91CC-524E37547BC3</incoming>
         <outgoing>sid-BE69BA84-146E-45A9-B387-4F0898C83059</outgoing>
      </exclusiveGateway>
      <endEvent id="sid-8CF02890-16FE-4414-9B3F-E2F0B5B49F15" name="End Farming">
         <extensionElements>
            <signavio:signavioMetaData metaKey="bgcolor" metaValue="#ffffff"/>
            <signavio:signavioMetaData metaKey="bordercolor" metaValue="#000000"/>
            <signavio:signavioMetaData metaKey="nachfolgerprozesse" metaValue="[]"/>
         </extensionElements>
         <incoming>sid-BE69BA84-146E-45A9-B387-4F0898C83059</incoming>
      </endEvent>
      <userTask completionQuantity="1" id="sid-4B6AFED9-ECB7-4D76-B7BF-600982C3A1F4" implementation="##WebService" isForCompensation="false" name="brag and send materials to friends" startQuantity="1">
         <extensionElements>
            <signavio:signavioMetaData metaKey="bgcolor" metaValue="#FFFFCC"/>
            <signavio:signavioMetaData metaKey="bordercolor" metaValue="#000000"/>
            <signavio:signavioMetaData metaKey="erteiltfreigabe" metaValue=""/>
            <signavio:signavioMetaData metaKey="wirdkonsultiert" metaValue="[]"/>
            <signavio:signavioMetaData metaKey="externaldocuments" metaValue="[]"/>
            <signavio:signavioMetaData metaKey="meta-risikomanagement" metaValue=""/>
            <signavio:signavioMetaData metaKey="wirdinformiert" metaValue="[]"/>
         </extensionElements>
         <incoming>sid-EAE6212D-1F02-445E-BC43-69EDBBE56BB1</incoming>
         <outgoing>sid-3639D970-8627-48EE-91CC-524E37547BC3</outgoing>
      </userTask>
      <exclusiveGateway gatewayDirection="Diverging" id="sid-69A5168B-B590-4025-BB44-9C7C9BD263E4" name="natural disaster?">
         <extensionElements>
            <signavio:signavioMetaData metaKey="bgcolor" metaValue="#ffffff"/>
            <signavio:signavioMetaData metaKey="bordercolor" metaValue="#000000"/>
            <signavio:signavioLabel align="center" bottom="false" left="false" ref="text_name" right="false" top="true" valign="bottom" x="20.0" y="-8.0"/>
         </extensionElements>
         <incoming>sid-18E5ED83-8FE7-476E-87F0-3D326319AB8D</incoming>
         <outgoing>sid-5B5C9300-5396-4EF0-8F52-9B5E03F40CFD</outgoing>
         <outgoing>sid-84524D0F-BB6C-4CE0-9054-A41FABFE8125</outgoing>
      </exclusiveGateway>
      <serviceTask completionQuantity="1" id="sid-CB974ECB-BE0B-48AF-B590-2D3195BC6F8D" implementation="##WebService" isForCompensation="false" name="set bot back" startQuantity="1">
         <extensionElements>
            <signavio:signavioMetaData metaKey="bgcolor" metaValue="#ffffcc"/>
            <signavio:signavioMetaData metaKey="bordercolor" metaValue="#000000"/>
            <signavio:signavioMetaData metaKey="erteiltfreigabe" metaValue=""/>
            <signavio:signavioMetaData metaKey="wirdkonsultiert" metaValue="[]"/>
            <signavio:signavioMetaData metaKey="externaldocuments" metaValue="[]"/>
            <signavio:signavioMetaData metaKey="meta-risikomanagement" metaValue=""/>
            <signavio:signavioMetaData metaKey="wirdinformiert" metaValue="[]"/>
         </extensionElements>
         <incoming>sid-5B5C9300-5396-4EF0-8F52-9B5E03F40CFD</incoming>
         <outgoing>sid-C495992A-A7A0-4F3C-BCDB-29E783B5171F</outgoing>
      </serviceTask>
      <serviceTask completionQuantity="1" id="sid-459CC583-20CC-46D9-A6E2-56B0F507912C" implementation="##WebService" isForCompensation="false" name="notify about new Milestone" startQuantity="1">
         <extensionElements>
            <signavio:signavioMetaData metaKey="bgcolor" metaValue="#FFFFCC"/>
            <signavio:signavioMetaData metaKey="bordercolor" metaValue="#000000"/>
            <signavio:signavioMetaData metaKey="erteiltfreigabe" metaValue=""/>
            <signavio:signavioMetaData metaKey="wirdkonsultiert" metaValue="[]"/>
            <signavio:signavioMetaData metaKey="externaldocuments" metaValue="[]"/>
            <signavio:signavioMetaData metaKey="meta-risikomanagement" metaValue=""/>
            <signavio:signavioMetaData metaKey="wirdinformiert" metaValue="[]"/>
         </extensionElements>
         <incoming>sid-476415BF-4006-4267-B64E-A38D9070B551</incoming>
         <outgoing>sid-3DD93327-5EE9-477A-B9F0-3AC97BC266D5</outgoing>
      </serviceTask>
      <exclusiveGateway gatewayDirection="Diverging" id="sid-8E40E2E5-D9F1-43F8-AA5B-BCDF270149E7" name="Milestone?">
         <extensionElements>
            <signavio:signavioMetaData metaKey="bgcolor" metaValue="#ffffff"/>
            <signavio:signavioMetaData metaKey="bordercolor" metaValue="#000000"/>
            <signavio:signavioLabel align="center" bottom="false" left="false" ref="text_name" right="false" top="true" valign="bottom" x="20.0" y="-8.0"/>
         </extensionElements>
         <incoming>sid-9AC2A839-2F4E-460C-975B-99F75B4D3A49</incoming>
         <outgoing>sid-476415BF-4006-4267-B64E-A38D9070B551</outgoing>
         <outgoing>sid-FC8C2850-D4F9-49D3-920D-478EC772157C</outgoing>
      </exclusiveGateway>
      <serviceTask completionQuantity="1" id="sid-6BFC7FF3-96DF-43A2-9269-22B4C475EEBD" implementation="##WebService" isForCompensation="false" name="Farming" startQuantity="1">
         <extensionElements>
            <signavio:signavioMetaData metaKey="bgcolor" metaValue="#ffffcc"/>
            <signavio:signavioMetaData metaKey="bordercolor" metaValue="#000000"/>
            <signavio:signavioMetaData metaKey="erteiltfreigabe" metaValue=""/>
            <signavio:signavioMetaData metaKey="wirdkonsultiert" metaValue="[]"/>
            <signavio:signavioMetaData metaKey="externaldocuments" metaValue="[]"/>
            <signavio:signavioMetaData metaKey="meta-risikomanagement" metaValue=""/>
            <signavio:signavioMetaData metaKey="wirdinformiert" metaValue="[]"/>
         </extensionElements>
         <incoming>sid-D40131F1-8E29-461E-B48A-FA019E7E09CC</incoming>
         <outgoing>sid-915B71D0-562C-4BAB-9FFB-A65C6DC9D4A5</outgoing>
      </serviceTask>
      <serviceTask completionQuantity="1" id="sid-C46919CE-C515-4092-B5DC-36A012476AE8" implementation="##WebService" isForCompensation="false" name="Farming ended" startQuantity="1">
         <extensionElements>
            <signavio:signavioMetaData metaKey="bgcolor" metaValue="#ffffcc"/>
            <signavio:signavioMetaData metaKey="bordercolor" metaValue="#000000"/>
            <signavio:signavioMetaData metaKey="erteiltfreigabe" metaValue=""/>
            <signavio:signavioMetaData metaKey="wirdkonsultiert" metaValue="[]"/>
            <signavio:signavioMetaData metaKey="externaldocuments" metaValue="[]"/>
            <signavio:signavioMetaData metaKey="meta-risikomanagement" metaValue=""/>
            <signavio:signavioMetaData metaKey="wirdinformiert" metaValue="[]"/>
         </extensionElements>
         <incoming>sid-9B832B97-59F8-4F69-82E3-B206C50BAE9C</incoming>
         <outgoing>sid-314D740D-DE5E-4ADE-A717-7F68D0EC996E</outgoing>
      </serviceTask>
      <exclusiveGateway gatewayDirection="Unspecified" id="sid-7AC1439B-F977-44D0-BD81-AA73D744F985" name="">
         <extensionElements>
            <signavio:signavioMetaData metaKey="bgcolor" metaValue="#ffffff"/>
            <signavio:signavioMetaData metaKey="bordercolor" metaValue="#000000"/>
            <signavio:signavioLabel align="center" ref="text_name" valign="middle" x="-31.0" y="4.0"/>
         </extensionElements>
         <incoming>sid-84524D0F-BB6C-4CE0-9054-A41FABFE8125</incoming>
         <outgoing>sid-A3542E81-0005-4019-A736-2790D24276C5</outgoing>
      </exclusiveGateway>
      <parallelGateway gatewayDirection="Diverging" id="sid-B053F60B-3197-4F90-9829-A4CDC7ED3B84" name="">
         <extensionElements>
            <signavio:signavioMetaData metaKey="bgcolor" metaValue="#ffffff"/>
            <signavio:signavioMetaData metaKey="bordercolor" metaValue="#000000"/>
         </extensionElements>
         <incoming>sid-915B71D0-562C-4BAB-9FFB-A65C6DC9D4A5</incoming>
         <outgoing>sid-18E5ED83-8FE7-476E-87F0-3D326319AB8D</outgoing>
         <outgoing>sid-C29E8122-E5AD-4431-A155-8979E7BDDDD5</outgoing>
         <outgoing>sid-9AC2A839-2F4E-460C-975B-99F75B4D3A49</outgoing>
      </parallelGateway>
      <parallelGateway gatewayDirection="Converging" id="sid-79623788-F448-42F1-B711-109493412590" name="">
         <extensionElements>
            <signavio:signavioMetaData metaKey="bgcolor" metaValue="#ffffff"/>
            <signavio:signavioMetaData metaKey="bordercolor" metaValue="#000000"/>
         </extensionElements>
         <incoming>sid-A3542E81-0005-4019-A736-2790D24276C5</incoming>
         <incoming>sid-4980AA18-39C9-4E54-B24C-0945A5134CCE</incoming>
         <incoming>sid-1AE36E8B-E1B1-4325-A9A3-8848B418606B</incoming>
         <outgoing>sid-82DE962F-B3B0-480E-AD90-2A6E0FFEEE11</outgoing>
      </parallelGateway>
      <exclusiveGateway gatewayDirection="Converging" id="sid-885A648A-B0C9-47D2-9624-906B1CC92140" name="">
         <extensionElements>
            <signavio:signavioMetaData metaKey="bgcolor" metaValue="#ffffff"/>
            <signavio:signavioMetaData metaKey="bordercolor" metaValue="#000000"/>
         </extensionElements>
         <incoming>sid-A80FA3E6-7C70-4133-A09C-819AEE471673</incoming>
         <incoming>sid-841E157A-8C25-4D60-9EC4-822EA7AD8022</incoming>
         <incoming>sid-C495992A-A7A0-4F3C-BCDB-29E783B5171F</incoming>
         <outgoing>sid-D40131F1-8E29-461E-B48A-FA019E7E09CC</outgoing>
      </exclusiveGateway>
      <exclusiveGateway gatewayDirection="Diverging" id="sid-C429E5F8-145E-4C77-942A-508E2FD37DE3" name="continue Farming?">
         <extensionElements>
            <signavio:signavioMetaData metaKey="bgcolor" metaValue="#ffffff"/>
            <signavio:signavioMetaData metaKey="bordercolor" metaValue="#000000"/>
            <signavio:signavioLabel align="center" bottom="true" left="false" ref="text_name" right="false" top="false" x="20.0" y="45.0"/>
         </extensionElements>
         <incoming>sid-FA741551-BC7A-4041-A159-4493B3F4B95B</incoming>
         <outgoing>sid-9B832B97-59F8-4F69-82E3-B206C50BAE9C</outgoing>
         <outgoing>sid-841E157A-8C25-4D60-9EC4-822EA7AD8022</outgoing>
      </exclusiveGateway>
      <exclusiveGateway gatewayDirection="Converging" id="sid-2815C8D6-40FD-41A6-BB74-6F10C4E0BEEF" name="">
         <extensionElements>
            <signavio:signavioMetaData metaKey="bgcolor" metaValue="#ffffff"/>
            <signavio:signavioMetaData metaKey="bordercolor" metaValue="#000000"/>
         </extensionElements>
         <incoming>sid-AFC848A3-F230-452C-A79F-2372D0D24F7F</incoming>
         <incoming>sid-F64341FD-A44D-4B9B-984B-0B20BD9E9384</incoming>
         <outgoing>sid-4980AA18-39C9-4E54-B24C-0945A5134CCE</outgoing>
      </exclusiveGateway>
      <exclusiveGateway gatewayDirection="Converging" id="sid-59C95768-76C7-461E-BEC4-55D9EF1727BA" name="">
         <extensionElements>
            <signavio:signavioMetaData metaKey="bgcolor" metaValue="#ffffff"/>
            <signavio:signavioMetaData metaKey="bordercolor" metaValue="#000000"/>
         </extensionElements>
         <incoming>sid-3DD93327-5EE9-477A-B9F0-3AC97BC266D5</incoming>
         <incoming>sid-FC8C2850-D4F9-49D3-920D-478EC772157C</incoming>
         <outgoing>sid-1AE36E8B-E1B1-4325-A9A3-8848B418606B</outgoing>
      </exclusiveGateway>
      <serviceTask completionQuantity="1" id="sid-06562524-6558-43F4-99A3-88883DBB94C8" implementation="##WebService" isForCompensation="false" name="save recources" startQuantity="1">
         <extensionElements>
            <signavio:signavioMetaData metaKey="bgcolor" metaValue="#ffffcc"/>
            <signavio:signavioMetaData metaKey="bordercolor" metaValue="#000000"/>
            <signavio:signavioMetaData metaKey="erteiltfreigabe" metaValue=""/>
            <signavio:signavioMetaData metaKey="wirdkonsultiert" metaValue="[]"/>
            <signavio:signavioMetaData metaKey="externaldocuments" metaValue="[]"/>
            <signavio:signavioMetaData metaKey="meta-risikomanagement" metaValue=""/>
            <signavio:signavioMetaData metaKey="wirdinformiert" metaValue="[]"/>
         </extensionElements>
         <incoming>sid-82DE962F-B3B0-480E-AD90-2A6E0FFEEE11</incoming>
         <outgoing>sid-FA741551-BC7A-4041-A159-4493B3F4B95B</outgoing>
      </serviceTask>
      <sequenceFlow id="sid-915B71D0-562C-4BAB-9FFB-A65C6DC9D4A5" name="" sourceRef="sid-6BFC7FF3-96DF-43A2-9269-22B4C475EEBD" targetRef="sid-B053F60B-3197-4F90-9829-A4CDC7ED3B84">
         <extensionElements>
            <signavio:signavioMetaData metaKey="bordercolor" metaValue="#000000"/>
         </extensionElements>
      </sequenceFlow>
      <sequenceFlow id="sid-18E5ED83-8FE7-476E-87F0-3D326319AB8D" name="" sourceRef="sid-B053F60B-3197-4F90-9829-A4CDC7ED3B84" targetRef="sid-69A5168B-B590-4025-BB44-9C7C9BD263E4">
         <extensionElements>
            <signavio:signavioMetaData metaKey="bordercolor" metaValue="#000000"/>
         </extensionElements>
      </sequenceFlow>
      <sequenceFlow id="sid-E0704CB7-47D0-4C8D-99E4-C30091DF8219" name="" sourceRef="sid-AECEBC4B-A695-4F3D-8F32-48D648544277" targetRef="sid-94315044-9369-43F1-AF4F-309996396228">
         <extensionElements>
            <signavio:signavioMetaData metaKey="bordercolor" metaValue="#000000"/>
         </extensionElements>
      </sequenceFlow>
      <sequenceFlow id="sid-9B38DB9C-7620-49F5-9316-A37894EFB89B" name="" sourceRef="sid-C6E897EF-0C45-4A5C-9F96-9E57B03064BE" targetRef="sid-94315044-9369-43F1-AF4F-309996396228">
         <extensionElements>
            <signavio:signavioMetaData metaKey="bordercolor" metaValue="#000000"/>
         </extensionElements>
      </sequenceFlow>
      <sequenceFlow id="sid-BE69BA84-146E-45A9-B387-4F0898C83059" name="" sourceRef="sid-94315044-9369-43F1-AF4F-309996396228" targetRef="sid-8CF02890-16FE-4414-9B3F-E2F0B5B49F15">
         <extensionElements>
            <signavio:signavioMetaData metaKey="bordercolor" metaValue="#000000"/>
         </extensionElements>
      </sequenceFlow>
      <sequenceFlow id="sid-3639D970-8627-48EE-91CC-524E37547BC3" name="" sourceRef="sid-4B6AFED9-ECB7-4D76-B7BF-600982C3A1F4" targetRef="sid-94315044-9369-43F1-AF4F-309996396228">
         <extensionElements>
            <signavio:signavioMetaData metaKey="bordercolor" metaValue="#000000"/>
         </extensionElements>
      </sequenceFlow>
      <sequenceFlow id="sid-EAE6212D-1F02-445E-BC43-69EDBBE56BB1" name="both" sourceRef="sid-36AE0908-FCB7-44CB-B542-915C24B8794A" targetRef="sid-4B6AFED9-ECB7-4D76-B7BF-600982C3A1F4">
         <extensionElements>
            <signavio:signavioMetaData metaKey="bordercolor" metaValue="#000000"/>
         </extensionElements>
      </sequenceFlow>
      <sequenceFlow id="sid-A80FA3E6-7C70-4133-A09C-819AEE471673" name="" sourceRef="sid-995C1ED2-823B-4D1B-A156-30C091163C03" targetRef="sid-885A648A-B0C9-47D2-9624-906B1CC92140">
         <extensionElements>
            <signavio:signavioMetaData metaKey="bordercolor" metaValue="#000000"/>
         </extensionElements>
      </sequenceFlow>
      <sequenceFlow id="sid-314D740D-DE5E-4ADE-A717-7F68D0EC996E" name="" sourceRef="sid-C46919CE-C515-4092-B5DC-36A012476AE8" targetRef="sid-36AE0908-FCB7-44CB-B542-915C24B8794A">
         <extensionElements>
            <signavio:signavioMetaData metaKey="bordercolor" metaValue="#000000"/>
         </extensionElements>
      </sequenceFlow>
      <sequenceFlow id="sid-82DE962F-B3B0-480E-AD90-2A6E0FFEEE11" name="" sourceRef="sid-79623788-F448-42F1-B711-109493412590" targetRef="sid-06562524-6558-43F4-99A3-88883DBB94C8">
         <extensionElements>
            <signavio:signavioMetaData metaKey="bordercolor" metaValue="#000000"/>
         </extensionElements>
      </sequenceFlow>
      <sequenceFlow id="sid-1168F775-4B9E-42B6-A602-4DE7F0193063" name="send" sourceRef="sid-36AE0908-FCB7-44CB-B542-915C24B8794A" targetRef="sid-C6E897EF-0C45-4A5C-9F96-9E57B03064BE">
         <extensionElements>
            <signavio:signavioMetaData metaKey="bordercolor" metaValue="#000000"/>
            <signavio:signavioLabel edge="startbottom" ref="text_name"/>
         </extensionElements>
      </sequenceFlow>
      <sequenceFlow id="sid-E1940EFA-FFDB-4513-8CF5-385595943FED" name="brag" sourceRef="sid-36AE0908-FCB7-44CB-B542-915C24B8794A" targetRef="sid-AECEBC4B-A695-4F3D-8F32-48D648544277">
         <extensionElements>
            <signavio:signavioMetaData metaKey="bordercolor" metaValue="#000000"/>
            <signavio:signavioLabel edge="startbottom" ref="text_name"/>
         </extensionElements>
      </sequenceFlow>
      <sequenceFlow id="sid-D40131F1-8E29-461E-B48A-FA019E7E09CC" name="" sourceRef="sid-885A648A-B0C9-47D2-9624-906B1CC92140" targetRef="sid-6BFC7FF3-96DF-43A2-9269-22B4C475EEBD">
         <extensionElements>
            <signavio:signavioMetaData metaKey="bordercolor" metaValue="#000000"/>
         </extensionElements>
      </sequenceFlow>
      <sequenceFlow id="sid-C29E8122-E5AD-4431-A155-8979E7BDDDD5" name="" sourceRef="sid-B053F60B-3197-4F90-9829-A4CDC7ED3B84" targetRef="sid-72387810-5DD4-4BC7-98B5-C0D192A43F71">
         <extensionElements>
            <signavio:signavioMetaData metaKey="bordercolor" metaValue="#000000"/>
         </extensionElements>
      </sequenceFlow>
      <sequenceFlow id="sid-476415BF-4006-4267-B64E-A38D9070B551" name="Yes" sourceRef="sid-8E40E2E5-D9F1-43F8-AA5B-BCDF270149E7" targetRef="sid-459CC583-20CC-46D9-A6E2-56B0F507912C">
         <extensionElements>
            <signavio:signavioMetaData metaKey="bordercolor" metaValue="#000000"/>
         </extensionElements>
      </sequenceFlow>
      <sequenceFlow id="sid-4557CBC3-5064-4412-9BE8-CFF545235FE6" name="Yes" sourceRef="sid-72387810-5DD4-4BC7-98B5-C0D192A43F71" targetRef="sid-8A17AEF6-4F45-449B-9E37-C93642245520">
         <extensionElements>
            <signavio:signavioMetaData metaKey="bordercolor" metaValue="#000000"/>
         </extensionElements>
      </sequenceFlow>
      <sequenceFlow id="sid-3DD93327-5EE9-477A-B9F0-3AC97BC266D5" name="" sourceRef="sid-459CC583-20CC-46D9-A6E2-56B0F507912C" targetRef="sid-59C95768-76C7-461E-BEC4-55D9EF1727BA">
         <extensionElements>
            <signavio:signavioMetaData metaKey="bordercolor" metaValue="#000000"/>
         </extensionElements>
      </sequenceFlow>
      <sequenceFlow id="sid-A3542E81-0005-4019-A736-2790D24276C5" name="" sourceRef="sid-7AC1439B-F977-44D0-BD81-AA73D744F985" targetRef="sid-79623788-F448-42F1-B711-109493412590">
         <extensionElements>
            <signavio:signavioMetaData metaKey="bordercolor" metaValue="#000000"/>
         </extensionElements>
      </sequenceFlow>
      <sequenceFlow id="sid-9B832B97-59F8-4F69-82E3-B206C50BAE9C" name="No" sourceRef="sid-C429E5F8-145E-4C77-942A-508E2FD37DE3" targetRef="sid-C46919CE-C515-4092-B5DC-36A012476AE8">
         <extensionElements>
            <signavio:signavioMetaData metaKey="bordercolor" metaValue="#000000"/>
         </extensionElements>
      </sequenceFlow>
      <sequenceFlow id="sid-752C7D6F-B222-4C87-A0C2-F68190C73039" name="" sourceRef="sid-FCD05023-BAA3-4065-BD1F-5FA697C9FE7E" targetRef="sid-995C1ED2-823B-4D1B-A156-30C091163C03">
         <extensionElements>
            <signavio:signavioMetaData metaKey="bordercolor" metaValue="#000000"/>
         </extensionElements>
      </sequenceFlow>
      <sequenceFlow id="sid-AFC848A3-F230-452C-A79F-2372D0D24F7F" name="" sourceRef="sid-8A17AEF6-4F45-449B-9E37-C93642245520" targetRef="sid-2815C8D6-40FD-41A6-BB74-6F10C4E0BEEF">
         <extensionElements>
            <signavio:signavioMetaData metaKey="bordercolor" metaValue="#000000"/>
         </extensionElements>
      </sequenceFlow>
      <sequenceFlow id="sid-4980AA18-39C9-4E54-B24C-0945A5134CCE" name="" sourceRef="sid-2815C8D6-40FD-41A6-BB74-6F10C4E0BEEF" targetRef="sid-79623788-F448-42F1-B711-109493412590">
         <extensionElements>
            <signavio:signavioMetaData metaKey="bordercolor" metaValue="#000000"/>
         </extensionElements>
      </sequenceFlow>
      <sequenceFlow id="sid-F64341FD-A44D-4B9B-984B-0B20BD9E9384" name="No" sourceRef="sid-72387810-5DD4-4BC7-98B5-C0D192A43F71" targetRef="sid-2815C8D6-40FD-41A6-BB74-6F10C4E0BEEF">
         <extensionElements>
            <signavio:signavioMetaData metaKey="bordercolor" metaValue="#000000"/>
         </extensionElements>
      </sequenceFlow>
      <sequenceFlow id="sid-9AC2A839-2F4E-460C-975B-99F75B4D3A49" name="" sourceRef="sid-B053F60B-3197-4F90-9829-A4CDC7ED3B84" targetRef="sid-8E40E2E5-D9F1-43F8-AA5B-BCDF270149E7">
         <extensionElements>
            <signavio:signavioMetaData metaKey="bordercolor" metaValue="#000000"/>
         </extensionElements>
      </sequenceFlow>
      <sequenceFlow id="sid-1AE36E8B-E1B1-4325-A9A3-8848B418606B" name="" sourceRef="sid-59C95768-76C7-461E-BEC4-55D9EF1727BA" targetRef="sid-79623788-F448-42F1-B711-109493412590">
         <extensionElements>
            <signavio:signavioMetaData metaKey="bordercolor" metaValue="#000000"/>
         </extensionElements>
      </sequenceFlow>
      <sequenceFlow id="sid-FC8C2850-D4F9-49D3-920D-478EC772157C" name="No" sourceRef="sid-8E40E2E5-D9F1-43F8-AA5B-BCDF270149E7" targetRef="sid-59C95768-76C7-461E-BEC4-55D9EF1727BA">
         <extensionElements>
            <signavio:signavioMetaData metaKey="bordercolor" metaValue="#000000"/>
         </extensionElements>
      </sequenceFlow>
      <sequenceFlow id="sid-FA741551-BC7A-4041-A159-4493B3F4B95B" name="" sourceRef="sid-06562524-6558-43F4-99A3-88883DBB94C8" targetRef="sid-C429E5F8-145E-4C77-942A-508E2FD37DE3">
         <extensionElements>
            <signavio:signavioMetaData metaKey="bordercolor" metaValue="#000000"/>
         </extensionElements>
      </sequenceFlow>
      <sequenceFlow id="sid-841E157A-8C25-4D60-9EC4-822EA7AD8022" name="Yes" sourceRef="sid-C429E5F8-145E-4C77-942A-508E2FD37DE3" targetRef="sid-885A648A-B0C9-47D2-9624-906B1CC92140">
         <extensionElements>
            <signavio:signavioMetaData metaKey="bordercolor" metaValue="#000000"/>
         </extensionElements>
      </sequenceFlow>
      <sequenceFlow id="sid-C495992A-A7A0-4F3C-BCDB-29E783B5171F" name="" sourceRef="sid-CB974ECB-BE0B-48AF-B590-2D3195BC6F8D" targetRef="sid-885A648A-B0C9-47D2-9624-906B1CC92140">
         <extensionElements>
            <signavio:signavioMetaData metaKey="bordercolor" metaValue="#000000"/>
         </extensionElements>
      </sequenceFlow>
      <sequenceFlow id="sid-5B5C9300-5396-4EF0-8F52-9B5E03F40CFD" name="Yes" sourceRef="sid-69A5168B-B590-4025-BB44-9C7C9BD263E4" targetRef="sid-CB974ECB-BE0B-48AF-B590-2D3195BC6F8D">
         <extensionElements>
            <signavio:signavioMetaData metaKey="bordercolor" metaValue="#000000"/>
         </extensionElements>
      </sequenceFlow>
      <sequenceFlow id="sid-84524D0F-BB6C-4CE0-9054-A41FABFE8125" name="No" sourceRef="sid-69A5168B-B590-4025-BB44-9C7C9BD263E4" targetRef="sid-7AC1439B-F977-44D0-BD81-AA73D744F985">
         <extensionElements>
            <signavio:signavioMetaData metaKey="bordercolor" metaValue="#000000"/>
         </extensionElements>
      </sequenceFlow>
      <association associationDirection="None" id="sid-208DAF48-00C4-4585-979B-FABADE3E8A02" sourceRef="sid-995C1ED2-823B-4D1B-A156-30C091163C03" targetRef="sid-C83DCA5C-343B-4103-AE2C-EAB40C19B834">
         <extensionElements>
            <signavio:signavioMetaData metaKey="bordercolor" metaValue="#000000"/>
         </extensionElements>
      </association>
      <textAnnotation id="sid-C83DCA5C-343B-4103-AE2C-EAB40C19B834" signavio:alignment="left" textFormat="text/plain">
         <extensionElements>
            <signavio:signavioMetaData metaKey="bordercolor" metaValue="#000000"/>
         </extensionElements>
         <text>Branch
Wood
Stone
Iron
Gold
Diamond
Meat
Berry
Fruit
Water
Coal
Sword (1 wood &amp; 3 irons)
Pickaxe (2 branches &amp; 1 iron)
Ax (2 branches &amp; 1 iron)</text>
      </textAnnotation>
   </process>
   <bpmndi:BPMNDiagram id="sid-2422e01b-6698-4355-9ddf-fa76c375f807">
      <bpmndi:BPMNPlane bpmnElement="sid-a0885187-eeca-4f85-bd14-b108c6867dac" id="sid-09000a0a-b0d4-431e-8b94-fdf1af1ab93d">
         <bpmndi:BPMNShape bpmnElement="sid-254C1C08-44FB-4435-B4CE-250D40804BB0" id="sid-254C1C08-44FB-4435-B4CE-250D40804BB0_gui" isHorizontal="true">
            <omgdc:Bounds height="468.0" width="1737.7249995456339" x="60.0" y="21.0"/>
            <bpmndi:BPMNLabel labelStyle="sid-4fe8bc70-0dfd-45c1-bf6a-c165da57e035">
               <omgdc:Bounds height="66.34285736083984" width="12.000000000000014" x="65.0" y="221.82857131958008"/>
            </bpmndi:BPMNLabel>
         </bpmndi:BPMNShape>
         <bpmndi:BPMNShape bpmnElement="sid-02EB9EA9-F233-448D-90FD-457933AC17F3" id="sid-02EB9EA9-F233-448D-90FD-457933AC17F3_gui" isHorizontal="true">
            <omgdc:Bounds height="468.0" width="1707.7249995456339" x="90.0" y="21.0"/>
         </bpmndi:BPMNShape>
         <bpmndi:BPMNShape bpmnElement="sid-FCD05023-BAA3-4065-BD1F-5FA697C9FE7E" id="sid-FCD05023-BAA3-4065-BD1F-5FA697C9FE7E_gui">
            <omgdc:Bounds height="30.0" width="30.0" x="108.8999981825352" y="202.0"/>
            <bpmndi:BPMNLabel labelStyle="sid-c83480c6-60dd-413d-8262-55e70331336b">
               <omgdc:Bounds height="11.0" width="25.45714569091797" x="111.17142533707622" y="234.0"/>
            </bpmndi:BPMNLabel>
         </bpmndi:BPMNShape>
         <bpmndi:BPMNShape bpmnElement="sid-995C1ED2-823B-4D1B-A156-30C091163C03" id="sid-995C1ED2-823B-4D1B-A156-30C091163C03_gui">
            <omgdc:Bounds height="80.0" width="100.00000000000003" x="183.8999981825352" y="177.0"/>
            <bpmndi:BPMNLabel labelStyle="sid-4fe8bc70-0dfd-45c1-bf6a-c165da57e035">
               <omgdc:Bounds height="36.0" width="52.457138061523466" x="207.67142915177348" y="197.0"/>
            </bpmndi:BPMNLabel>
         </bpmndi:BPMNShape>
         <bpmndi:BPMNShape bpmnElement="sid-8A17AEF6-4F45-449B-9E37-C93642245520" id="sid-8A17AEF6-4F45-449B-9E37-C93642245520_gui">
            <omgdc:Bounds height="80.0" width="100.0" x="746.2253603716888" y="177.52758362816877"/>
            <bpmndi:BPMNLabel labelStyle="sid-4fe8bc70-0dfd-45c1-bf6a-c165da57e035">
               <omgdc:Bounds height="12.0" width="77.9142837524414" x="757.2682184954681" y="209.52758362816877"/>
            </bpmndi:BPMNLabel>
         </bpmndi:BPMNShape>
         <bpmndi:BPMNShape bpmnElement="sid-72387810-5DD4-4BC7-98B5-C0D192A43F71" id="sid-72387810-5DD4-4BC7-98B5-C0D192A43F71_gui" isMarkerVisible="true">
            <omgdc:Bounds height="40.0" width="40.0" x="639.8496364477483" y="197.52758362816877"/>
            <bpmndi:BPMNLabel labelStyle="sid-c83480c6-60dd-413d-8262-55e70331336b">
               <omgdc:Bounds height="12.0" width="126.5142822265625" x="596.592495334467" y="177.52758362816877"/>
            </bpmndi:BPMNLabel>
         </bpmndi:BPMNShape>
         <bpmndi:BPMNShape bpmnElement="sid-36AE0908-FCB7-44CB-B542-915C24B8794A" id="sid-36AE0908-FCB7-44CB-B542-915C24B8794A_gui" isMarkerVisible="true">
            <omgdc:Bounds height="40.0" width="40.0" x="1427.7249995456339" y="196.0"/>
         </bpmndi:BPMNShape>
         <bpmndi:BPMNShape bpmnElement="sid-AECEBC4B-A695-4F3D-8F32-48D648544277" id="sid-AECEBC4B-A695-4F3D-8F32-48D648544277_gui">
            <omgdc:Bounds height="80.0" width="100.0" x="1512.7249995456339" y="76.0"/>
            <bpmndi:BPMNLabel labelStyle="sid-4fe8bc70-0dfd-45c1-bf6a-c165da57e035">
               <omgdc:Bounds height="12.0" width="81.0" x="1522.2249995456339" y="108.0"/>
            </bpmndi:BPMNLabel>
         </bpmndi:BPMNShape>
         <bpmndi:BPMNShape bpmnElement="sid-C6E897EF-0C45-4A5C-9F96-9E57B03064BE" id="sid-C6E897EF-0C45-4A5C-9F96-9E57B03064BE_gui">
            <omgdc:Bounds height="80.0" width="100.0" x="1512.7249995456339" y="276.0"/>
            <bpmndi:BPMNLabel labelStyle="sid-4fe8bc70-0dfd-45c1-bf6a-c165da57e035">
               <omgdc:Bounds height="24.0" width="78.68571472167969" x="1523.382142184794" y="302.0"/>
            </bpmndi:BPMNLabel>
         </bpmndi:BPMNShape>
         <bpmndi:BPMNShape bpmnElement="sid-94315044-9369-43F1-AF4F-309996396228" id="sid-94315044-9369-43F1-AF4F-309996396228_gui" isMarkerVisible="true">
            <omgdc:Bounds height="40.0" width="40.0" x="1657.7249995456339" y="196.0"/>
         </bpmndi:BPMNShape>
         <bpmndi:BPMNShape bpmnElement="sid-8CF02890-16FE-4414-9B3F-E2F0B5B49F15" id="sid-8CF02890-16FE-4414-9B3F-E2F0B5B49F15_gui">
            <omgdc:Bounds height="28.0" width="28.0" x="1742.7249995456339" y="202.0"/>
            <bpmndi:BPMNLabel labelStyle="sid-c83480c6-60dd-413d-8262-55e70331336b">
               <omgdc:Bounds height="11.0" width="62.22857666015625" x="1725.6107112155557" y="232.0"/>
            </bpmndi:BPMNLabel>
         </bpmndi:BPMNShape>
         <bpmndi:BPMNShape bpmnElement="sid-4B6AFED9-ECB7-4D76-B7BF-600982C3A1F4" id="sid-4B6AFED9-ECB7-4D76-B7BF-600982C3A1F4_gui">
            <omgdc:Bounds height="80.0" width="100.0" x="1512.7249995456339" y="176.0"/>
            <bpmndi:BPMNLabel labelStyle="sid-4fe8bc70-0dfd-45c1-bf6a-c165da57e035">
               <omgdc:Bounds height="36.0" width="78.68571472167969" x="1523.382142184794" y="196.0"/>
            </bpmndi:BPMNLabel>
         </bpmndi:BPMNShape>
         <bpmndi:BPMNShape bpmnElement="sid-69A5168B-B590-4025-BB44-9C7C9BD263E4" id="sid-69A5168B-B590-4025-BB44-9C7C9BD263E4_gui" isMarkerVisible="true">
            <omgdc:Bounds height="40.0" width="40.0" x="639.8496364477483" y="316.0"/>
            <bpmndi:BPMNLabel labelStyle="sid-c83480c6-60dd-413d-8262-55e70331336b">
               <omgdc:Bounds height="12.0" width="91.02857208251953" x="614.3353504064885" y="296.0"/>
            </bpmndi:BPMNLabel>
         </bpmndi:BPMNShape>
         <bpmndi:BPMNShape bpmnElement="sid-CB974ECB-BE0B-48AF-B590-2D3195BC6F8D" id="sid-CB974ECB-BE0B-48AF-B590-2D3195BC6F8D_gui">
            <omgdc:Bounds height="80.0" width="100.0" x="746.2253603716888" y="347.0"/>
            <bpmndi:BPMNLabel labelStyle="sid-4fe8bc70-0dfd-45c1-bf6a-c165da57e035">
               <omgdc:Bounds height="12.0" width="67.88571166992188" x="762.2825045367279" y="379.0"/>
            </bpmndi:BPMNLabel>
         </bpmndi:BPMNShape>
         <bpmndi:BPMNShape bpmnElement="sid-459CC583-20CC-46D9-A6E2-56B0F507912C" id="sid-459CC583-20CC-46D9-A6E2-56B0F507912C_gui">
            <omgdc:Bounds height="80.0" width="99.99999999999989" x="746.2253603716888" y="59.05516725633754"/>
            <bpmndi:BPMNLabel labelStyle="sid-4fe8bc70-0dfd-45c1-bf6a-c165da57e035">
               <omgdc:Bounds height="24.0" width="91.80000305175781" x="750.3253588458099" y="85.05516725633754"/>
            </bpmndi:BPMNLabel>
         </bpmndi:BPMNShape>
         <bpmndi:BPMNShape bpmnElement="sid-8E40E2E5-D9F1-43F8-AA5B-BCDF270149E7" id="sid-8E40E2E5-D9F1-43F8-AA5B-BCDF270149E7_gui" isMarkerVisible="true">
            <omgdc:Bounds height="40.0" width="40.0" x="639.8496364477483" y="79.05516725633754"/>
            <bpmndi:BPMNLabel labelStyle="sid-c83480c6-60dd-413d-8262-55e70331336b">
               <omgdc:Bounds height="12.0" width="56.31428527832031" x="631.6924938085881" y="59.05516725633754"/>
            </bpmndi:BPMNLabel>
         </bpmndi:BPMNShape>
         <bpmndi:BPMNShape bpmnElement="sid-6BFC7FF3-96DF-43A2-9269-22B4C475EEBD" id="sid-6BFC7FF3-96DF-43A2-9269-22B4C475EEBD_gui">
            <omgdc:Bounds height="80.0" width="100.0" x="408.7249995456341" y="177.0"/>
            <bpmndi:BPMNLabel labelStyle="sid-4fe8bc70-0dfd-45c1-bf6a-c165da57e035">
               <omgdc:Bounds height="12.0" width="43.19999694824219" x="437.125001071513" y="209.0"/>
            </bpmndi:BPMNLabel>
         </bpmndi:BPMNShape>
         <bpmndi:BPMNShape bpmnElement="sid-C46919CE-C515-4092-B5DC-36A012476AE8" id="sid-C46919CE-C515-4092-B5DC-36A012476AE8_gui">
            <omgdc:Bounds height="80.0" width="100.0" x="1287.4499990912677" y="176.0"/>
            <bpmndi:BPMNLabel labelStyle="sid-4fe8bc70-0dfd-45c1-bf6a-c165da57e035">
               <omgdc:Bounds height="12.0" width="80.22857666015625" x="1297.3357107611896" y="208.0"/>
            </bpmndi:BPMNLabel>
         </bpmndi:BPMNShape>
         <bpmndi:BPMNShape bpmnElement="sid-7AC1439B-F977-44D0-BD81-AA73D744F985" id="sid-7AC1439B-F977-44D0-BD81-AA73D744F985_gui" isMarkerVisible="true">
            <omgdc:Bounds height="39.99999999999994" width="40.0" x="896.0007216521097" y="316.0"/>
         </bpmndi:BPMNShape>
         <bpmndi:BPMNShape bpmnElement="sid-B053F60B-3197-4F90-9829-A4CDC7ED3B84" id="sid-B053F60B-3197-4F90-9829-A4CDC7ED3B84_gui">
            <omgdc:Bounds height="40.0" width="40.0" x="556.4499990912678" y="197.0"/>
         </bpmndi:BPMNShape>
         <bpmndi:BPMNShape bpmnElement="sid-79623788-F448-42F1-B711-109493412590" id="sid-79623788-F448-42F1-B711-109493412590_gui">
            <omgdc:Bounds height="39.99999999999994" width="40.000000000000114" x="983.8999981825353" y="197.2889855866054"/>
         </bpmndi:BPMNShape>
         <bpmndi:BPMNShape bpmnElement="sid-885A648A-B0C9-47D2-9624-906B1CC92140" id="sid-885A648A-B0C9-47D2-9624-906B1CC92140_gui" isMarkerVisible="true">
            <omgdc:Bounds height="40.0" width="40.0" x="323.7249995456341" y="197.0"/>
         </bpmndi:BPMNShape>
         <bpmndi:BPMNShape bpmnElement="sid-C429E5F8-145E-4C77-942A-508E2FD37DE3" id="sid-C429E5F8-145E-4C77-942A-508E2FD37DE3_gui" isMarkerVisible="true">
            <omgdc:Bounds height="40.0" width="40.0" x="1206.901630238512" y="196.52758362816877"/>
            <bpmndi:BPMNLabel labelStyle="sid-c83480c6-60dd-413d-8262-55e70331336b">
               <omgdc:Bounds height="12.0" width="99.5142822265625" x="1177.1444891252308" y="241.52758362816877"/>
            </bpmndi:BPMNLabel>
         </bpmndi:BPMNShape>
         <bpmndi:BPMNShape bpmnElement="sid-2815C8D6-40FD-41A6-BB74-6F10C4E0BEEF" id="sid-2815C8D6-40FD-41A6-BB74-6F10C4E0BEEF_gui" isMarkerVisible="true">
            <omgdc:Bounds height="40.0" width="40.0" x="896.0007216521097" y="197.52758362816877"/>
         </bpmndi:BPMNShape>
         <bpmndi:BPMNShape bpmnElement="sid-59C95768-76C7-461E-BEC4-55D9EF1727BA" id="sid-59C95768-76C7-461E-BEC4-55D9EF1727BA_gui" isMarkerVisible="true">
            <omgdc:Bounds height="40.0" width="40.0" x="896.0007216521097" y="79.05516725633754"/>
         </bpmndi:BPMNShape>
         <bpmndi:BPMNShape bpmnElement="sid-06562524-6558-43F4-99A3-88883DBB94C8" id="sid-06562524-6558-43F4-99A3-88883DBB94C8_gui">
            <omgdc:Bounds height="80.0" width="100.0" x="1060.0" y="177.0"/>
            <bpmndi:BPMNLabel labelStyle="sid-4fe8bc70-0dfd-45c1-bf6a-c165da57e035">
               <omgdc:Bounds height="12.0" width="81.0" x="1069.5" y="209.0"/>
            </bpmndi:BPMNLabel>
         </bpmndi:BPMNShape>
         <bpmndi:BPMNShape bpmnElement="sid-C83DCA5C-343B-4103-AE2C-EAB40C19B834" id="sid-C83DCA5C-343B-4103-AE2C-EAB40C19B834_gui">
            <omgdc:Bounds height="189.0" width="185.0" x="140.89999818253523" y="281.0"/>
         </bpmndi:BPMNShape>
         <bpmndi:BPMNEdge bpmnElement="sid-915B71D0-562C-4BAB-9FFB-A65C6DC9D4A5" id="sid-915B71D0-562C-4BAB-9FFB-A65C6DC9D4A5_gui">
            <omgdi:waypoint x="508.7249995456341" y="217.21130019863364"/>
            <omgdi:waypoint x="556.4499990912678" y="217.41298623630928"/>
         </bpmndi:BPMNEdge>
         <bpmndi:BPMNEdge bpmnElement="sid-18E5ED83-8FE7-476E-87F0-3D326319AB8D" id="sid-18E5ED83-8FE7-476E-87F0-3D326319AB8D_gui">
            <omgdi:waypoint x="576.9499990912678" y="237.0"/>
            <omgdi:waypoint x="576.9499990912678" y="336.5"/>
            <omgdi:waypoint x="639.8496364477483" y="336.5"/>
         </bpmndi:BPMNEdge>
         <bpmndi:BPMNEdge bpmnElement="sid-E0704CB7-47D0-4C8D-99E4-C30091DF8219" id="sid-E0704CB7-47D0-4C8D-99E4-C30091DF8219_gui">
            <omgdi:waypoint x="1612.7249995456339" y="116.0"/>
            <omgdi:waypoint x="1678.2249995456339" y="116.0"/>
            <omgdi:waypoint x="1678.2249995456339" y="196.0"/>
         </bpmndi:BPMNEdge>
         <bpmndi:BPMNEdge bpmnElement="sid-9B38DB9C-7620-49F5-9316-A37894EFB89B" id="sid-9B38DB9C-7620-49F5-9316-A37894EFB89B_gui">
            <omgdi:waypoint x="1612.7249995456339" y="316.0"/>
            <omgdi:waypoint x="1678.2249995456339" y="316.0"/>
            <omgdi:waypoint x="1678.2249995456339" y="236.0"/>
         </bpmndi:BPMNEdge>
         <bpmndi:BPMNEdge bpmnElement="sid-BE69BA84-146E-45A9-B387-4F0898C83059" id="sid-BE69BA84-146E-45A9-B387-4F0898C83059_gui">
            <omgdi:waypoint x="1697.7249995456339" y="216.37579617834396"/>
            <omgdi:waypoint x="1742.7249995456339" y="216.0891719745223"/>
         </bpmndi:BPMNEdge>
         <bpmndi:BPMNEdge bpmnElement="sid-3639D970-8627-48EE-91CC-524E37547BC3" id="sid-3639D970-8627-48EE-91CC-524E37547BC3_gui">
            <omgdi:waypoint x="1612.7249995456339" y="216.21645021645023"/>
            <omgdi:waypoint x="1657.7249995456339" y="216.4112554112554"/>
         </bpmndi:BPMNEdge>
         <bpmndi:BPMNEdge bpmnElement="sid-EAE6212D-1F02-445E-BC43-69EDBBE56BB1" id="sid-EAE6212D-1F02-445E-BC43-69EDBBE56BB1_gui">
            <omgdi:waypoint x="1467.7249995456339" y="216.41484716157206"/>
            <omgdi:waypoint x="1512.7249995456339" y="216.2183406113537"/>
            <bpmndi:BPMNLabel labelStyle="sid-c83480c6-60dd-413d-8262-55e70331336b">
               <omgdc:Bounds height="12.111044389727653" width="25.509308692021477" x="1475.5566357047348" y="196.26909440144547"/>
            </bpmndi:BPMNLabel>
         </bpmndi:BPMNEdge>
         <bpmndi:BPMNEdge bpmnElement="sid-A80FA3E6-7C70-4133-A09C-819AEE471673" id="sid-A80FA3E6-7C70-4133-A09C-819AEE471673_gui">
            <omgdi:waypoint x="283.8999981825352" y="217.232542668499"/>
            <omgdi:waypoint x="323.7249995456341" y="217.409111062215"/>
         </bpmndi:BPMNEdge>
         <bpmndi:BPMNEdge bpmnElement="sid-314D740D-DE5E-4ADE-A717-7F68D0EC996E" id="sid-314D740D-DE5E-4ADE-A717-7F68D0EC996E_gui">
            <omgdi:waypoint x="1387.4499990912677" y="216.225682689212"/>
            <omgdi:waypoint x="1427.7249995456339" y="216.4074700974231"/>
         </bpmndi:BPMNEdge>
         <bpmndi:BPMNEdge bpmnElement="sid-208DAF48-00C4-4585-979B-FABADE3E8A02" id="sid-208DAF48-00C4-4585-979B-FABADE3E8A02_gui">
            <omgdi:waypoint x="183.8999981825352" y="240.13302325581395"/>
            <omgdi:waypoint x="170.8560551896611" y="281.0"/>
         </bpmndi:BPMNEdge>
         <bpmndi:BPMNEdge bpmnElement="sid-82DE962F-B3B0-480E-AD90-2A6E0FFEEE11" id="sid-82DE962F-B3B0-480E-AD90-2A6E0FFEEE11_gui">
            <omgdi:waypoint x="1023.8999981825355" y="217.64329222794996"/>
            <omgdi:waypoint x="1060.0" y="217.37357271450108"/>
         </bpmndi:BPMNEdge>
         <bpmndi:BPMNEdge bpmnElement="sid-1168F775-4B9E-42B6-A602-4DE7F0193063" id="sid-1168F775-4B9E-42B6-A602-4DE7F0193063_gui">
            <omgdi:waypoint x="1448.2249995456339" y="236.0"/>
            <omgdi:waypoint x="1448.2249995456339" y="316.0"/>
            <omgdi:waypoint x="1512.7249995456339" y="316.0"/>
            <bpmndi:BPMNLabel labelStyle="sid-c83480c6-60dd-413d-8262-55e70331336b">
               <omgdc:Bounds height="26.228515625" width="12.0" x="1456.2249995456339" y="244.00002395969636"/>
            </bpmndi:BPMNLabel>
         </bpmndi:BPMNEdge>
         <bpmndi:BPMNEdge bpmnElement="sid-E1940EFA-FFDB-4513-8CF5-385595943FED" id="sid-E1940EFA-FFDB-4513-8CF5-385595943FED_gui">
            <omgdi:waypoint x="1448.2249995456339" y="196.0"/>
            <omgdi:waypoint x="1448.2249995456339" y="116.0"/>
            <omgdi:waypoint x="1512.7249995456339" y="116.0"/>
            <bpmndi:BPMNLabel labelStyle="sid-c83480c6-60dd-413d-8262-55e70331336b">
               <omgdc:Bounds height="24.6856689453125" width="12.0" x="1456.2249995456339" y="163.31435501438386"/>
            </bpmndi:BPMNLabel>
         </bpmndi:BPMNEdge>
         <bpmndi:BPMNEdge bpmnElement="sid-D40131F1-8E29-461E-B48A-FA019E7E09CC" id="sid-D40131F1-8E29-461E-B48A-FA019E7E09CC_gui">
            <omgdi:waypoint x="363.7249995456341" y="217.41484716157206"/>
            <omgdi:waypoint x="408.7249995456341" y="217.2183406113537"/>
         </bpmndi:BPMNEdge>
         <bpmndi:BPMNEdge bpmnElement="sid-C29E8122-E5AD-4431-A155-8979E7BDDDD5" id="sid-C29E8122-E5AD-4431-A155-8979E7BDDDD5_gui">
            <omgdi:waypoint x="596.4499990912678" y="217.62335642066785"/>
            <omgdi:waypoint x="639.8496364477483" y="217.89790123721028"/>
         </bpmndi:BPMNEdge>
         <bpmndi:BPMNEdge bpmnElement="sid-476415BF-4006-4267-B64E-A38D9070B551" id="sid-476415BF-4006-4267-B64E-A38D9070B551_gui">
            <omgdi:waypoint x="679.8496364477483" y="99.05516725633754"/>
            <omgdi:waypoint x="746.2253603716888" y="99.05516725633754"/>
            <bpmndi:BPMNLabel labelStyle="sid-c83480c6-60dd-413d-8262-55e70331336b">
               <omgdc:Bounds height="12.0" width="19.28570556640625" x="687.3740234375" y="79.05500030517578"/>
            </bpmndi:BPMNLabel>
         </bpmndi:BPMNEdge>
         <bpmndi:BPMNEdge bpmnElement="sid-4557CBC3-5064-4412-9BE8-CFF545235FE6" id="sid-4557CBC3-5064-4412-9BE8-CFF545235FE6_gui">
            <omgdi:waypoint x="679.8496364477483" y="217.95582688076436"/>
            <omgdi:waypoint x="746.2253603716888" y="217.71157528818006"/>
            <bpmndi:BPMNLabel labelStyle="sid-c83480c6-60dd-413d-8262-55e70331336b">
               <omgdc:Bounds height="12.070889135256522" width="19.329734354570064" x="687.7083289900276" y="197.85571776376113"/>
            </bpmndi:BPMNLabel>
         </bpmndi:BPMNEdge>
         <bpmndi:BPMNEdge bpmnElement="sid-3DD93327-5EE9-477A-B9F0-3AC97BC266D5" id="sid-3DD93327-5EE9-477A-B9F0-3AC97BC266D5_gui">
            <omgdi:waypoint x="846.2253603716887" y="99.26302362636925"/>
            <omgdi:waypoint x="896.0007216521097" y="99.46994614462454"/>
         </bpmndi:BPMNEdge>
         <bpmndi:BPMNEdge bpmnElement="sid-A3542E81-0005-4019-A736-2790D24276C5" id="sid-A3542E81-0005-4019-A736-2790D24276C5_gui">
            <omgdi:waypoint x="936.0007216521097" y="336.5"/>
            <omgdi:waypoint x="1004.3999981825355" y="336.5"/>
            <omgdi:waypoint x="1004.3999981825355" y="237.28898558660535"/>
         </bpmndi:BPMNEdge>
         <bpmndi:BPMNEdge bpmnElement="sid-9B832B97-59F8-4F69-82E3-B206C50BAE9C" id="sid-9B832B97-59F8-4F69-82E3-B206C50BAE9C_gui">
            <omgdi:waypoint x="1246.901630238512" y="217.0226959523686"/>
            <omgdi:waypoint x="1287.4499990912677" y="217.01253250205176"/>
            <bpmndi:BPMNLabel labelStyle="sid-c83480c6-60dd-413d-8262-55e70331336b">
               <omgdc:Bounds height="12.003676646849073" width="14.660114468224947" x="1254.8919550837952" y="197.01731164419257"/>
            </bpmndi:BPMNLabel>
         </bpmndi:BPMNEdge>
         <bpmndi:BPMNEdge bpmnElement="sid-752C7D6F-B222-4C87-A0C2-F68190C73039" id="sid-752C7D6F-B222-4C87-A0C2-F68190C73039_gui">
            <omgdi:waypoint x="138.8999981825352" y="217.0"/>
            <omgdi:waypoint x="183.8999981825352" y="217.0"/>
         </bpmndi:BPMNEdge>
         <bpmndi:BPMNEdge bpmnElement="sid-AFC848A3-F230-452C-A79F-2372D0D24F7F" id="sid-AFC848A3-F230-452C-A79F-2372D0D24F7F_gui">
            <omgdi:waypoint x="846.2253603716888" y="217.73543999820046"/>
            <omgdi:waypoint x="896.0007216521097" y="217.94236251645577"/>
         </bpmndi:BPMNEdge>
         <bpmndi:BPMNEdge bpmnElement="sid-4980AA18-39C9-4E54-B24C-0945A5134CCE" id="sid-4980AA18-39C9-4E54-B24C-0945A5134CCE_gui">
            <omgdi:waypoint x="936.0007216521097" y="217.97465188636"/>
            <omgdi:waypoint x="983.8999981825353" y="217.84463177671205"/>
         </bpmndi:BPMNEdge>
         <bpmndi:BPMNEdge bpmnElement="sid-F64341FD-A44D-4B9B-984B-0B20BD9E9384" id="sid-F64341FD-A44D-4B9B-984B-0B20BD9E9384_gui">
            <omgdi:waypoint x="660.3496364477483" y="237.52758362816877"/>
            <omgdi:waypoint x="660.3496364477483" y="279.52758362816877"/>
            <omgdi:waypoint x="916.5007216521097" y="279.52758362816877"/>
            <omgdi:waypoint x="916.5007216521097" y="237.52758362816877"/>
            <bpmndi:BPMNLabel labelStyle="sid-c83480c6-60dd-413d-8262-55e70331336b">
               <omgdc:Bounds height="14.65716552734375" width="11.999999999999886" x="640.3500526975092" y="245.52724448997952"/>
            </bpmndi:BPMNLabel>
         </bpmndi:BPMNEdge>
         <bpmndi:BPMNEdge bpmnElement="sid-9AC2A839-2F4E-460C-975B-99F75B4D3A49" id="sid-9AC2A839-2F4E-460C-975B-99F75B4D3A49_gui">
            <omgdi:waypoint x="576.9499990912678" y="197.0"/>
            <omgdi:waypoint x="576.9499990912678" y="99.55516725633754"/>
            <omgdi:waypoint x="639.8496364477483" y="99.55516725633754"/>
         </bpmndi:BPMNEdge>
         <bpmndi:BPMNEdge bpmnElement="sid-1AE36E8B-E1B1-4325-A9A3-8848B418606B" id="sid-1AE36E8B-E1B1-4325-A9A3-8848B418606B_gui">
            <omgdi:waypoint x="936.0007216521097" y="99.55516725633754"/>
            <omgdi:waypoint x="1004.3999981825355" y="99.55516725633754"/>
            <omgdi:waypoint x="1004.3999981825355" y="197.2889855866054"/>
         </bpmndi:BPMNEdge>
         <bpmndi:BPMNEdge bpmnElement="sid-FC8C2850-D4F9-49D3-920D-478EC772157C" id="sid-FC8C2850-D4F9-49D3-920D-478EC772157C_gui">
            <omgdi:waypoint x="660.3496364477483" y="119.05516725633754"/>
            <omgdi:waypoint x="660.3496364477483" y="156.0"/>
            <omgdi:waypoint x="916.5007216521097" y="156.0"/>
            <omgdi:waypoint x="916.5007216521097" y="119.05516725633754"/>
            <bpmndi:BPMNLabel labelStyle="sid-c83480c6-60dd-413d-8262-55e70331336b">
               <omgdc:Bounds height="14.65716552734375" width="12.0" x="640.3494694965865" y="127.0548281181483"/>
            </bpmndi:BPMNLabel>
         </bpmndi:BPMNEdge>
         <bpmndi:BPMNEdge bpmnElement="sid-FA741551-BC7A-4041-A159-4493B3F4B95B" id="sid-FA741551-BC7A-4041-A159-4493B3F4B95B_gui">
            <omgdi:waypoint x="1160.0" y="217.0117475490386"/>
            <omgdi:waypoint x="1206.901630238512" y="217.02276713306296"/>
         </bpmndi:BPMNEdge>
         <bpmndi:BPMNEdge bpmnElement="sid-841E157A-8C25-4D60-9EC4-822EA7AD8022" id="sid-841E157A-8C25-4D60-9EC4-822EA7AD8022_gui">
            <omgdi:waypoint x="1227.401630238512" y="196.52758362816877"/>
            <omgdi:waypoint x="1227.401630238512" y="46.0"/>
            <omgdi:waypoint x="344.2249995456341" y="46.0"/>
            <omgdi:waypoint x="344.2249995456341" y="197.0"/>
            <bpmndi:BPMNLabel labelStyle="sid-c83480c6-60dd-413d-8262-55e70331336b">
               <omgdc:Bounds height="19.2857666015625" width="12.0" x="1207.402046488273" y="169.24146972605587"/>
            </bpmndi:BPMNLabel>
         </bpmndi:BPMNEdge>
         <bpmndi:BPMNEdge bpmnElement="sid-C495992A-A7A0-4F3C-BCDB-29E783B5171F" id="sid-C495992A-A7A0-4F3C-BCDB-29E783B5171F_gui">
            <omgdi:waypoint x="746.2253603716888" y="407.0"/>
            <omgdi:waypoint x="344.2249995456341" y="407.0"/>
            <omgdi:waypoint x="344.2249995456341" y="237.0"/>
         </bpmndi:BPMNEdge>
         <bpmndi:BPMNEdge bpmnElement="sid-5B5C9300-5396-4EF0-8F52-9B5E03F40CFD" id="sid-5B5C9300-5396-4EF0-8F52-9B5E03F40CFD_gui">
            <omgdi:waypoint x="660.3496364477483" y="356.0"/>
            <omgdi:waypoint x="660.3496364477483" y="387.5"/>
            <omgdi:waypoint x="746.2253603716888" y="387.5"/>
            <bpmndi:BPMNLabel labelStyle="sid-c83480c6-60dd-413d-8262-55e70331336b">
               <omgdc:Bounds height="19.28570556640625" width="12.0" x="640.3496364477483" y="363.99966086181075"/>
            </bpmndi:BPMNLabel>
         </bpmndi:BPMNEdge>
         <bpmndi:BPMNEdge bpmnElement="sid-84524D0F-BB6C-4CE0-9054-A41FABFE8125" id="sid-84524D0F-BB6C-4CE0-9054-A41FABFE8125_gui">
            <omgdi:waypoint x="679.8496364477483" y="336.5"/>
            <omgdi:waypoint x="896.0007216521097" y="336.5"/>
            <bpmndi:BPMNLabel labelStyle="sid-c83480c6-60dd-413d-8262-55e70331336b">
               <omgdc:Bounds height="12.0" width="14.65716552734375" x="687.8499755859375" y="316.5"/>
            </bpmndi:BPMNLabel>
         </bpmndi:BPMNEdge>
      </bpmndi:BPMNPlane>
      <bpmndi:BPMNLabelStyle id="sid-c83480c6-60dd-413d-8262-55e70331336b">
         <omgdc:Font isBold="false" isItalic="false" isStrikeThrough="false" isUnderline="false" name="Arial" size="11.0"/>
      </bpmndi:BPMNLabelStyle>
      <bpmndi:BPMNLabelStyle id="sid-4fe8bc70-0dfd-45c1-bf6a-c165da57e035">
         <omgdc:Font isBold="false" isItalic="false" isStrikeThrough="false" isUnderline="false" name="Arial" size="12.0"/>
      </bpmndi:BPMNLabelStyle>
   </bpmndi:BPMNDiagram>
</definitions>
